Workbook

Sheet Overzicht
C1: Factuuroverzicht
C2: Q4S B.V. · bedragen ex btw, tenzij anders vermeld
G4: Jaar | H4: 2026
H5: ▲ kies hier het jaar
C8: OMZET | D8: INKOOP FREELANCERS | E8: BRUTOMARGE | F8: KOSTEN | G8: WINST
C9: =C19 | D9: =D19 | E9: =E19 | F9: =F19 | G9: =G19
B12: Per kwartaal
B14: Kwartaal | C14: Omzet | D14: Inkoop freelancers | E14: Brutomarge | F14: Kosten | G14: Winst | H14: Btw afdragen
B15: Q1 | C15: =SUMIFS(Facturen!$M$6:$M$2000,Facturen!$Q$6:$Q$2000,">="&DATE($H$4,1,1),Facturen!$Q$6:$Q$2000,"<"&DATE($H$4,4,1)) | D15: =SUMIFS(Facturen!$G$6:$G$2000,Facturen!$A$6:$A$2000,">="&DATE($H$4,1,1),Facturen!$A$6:$A$2000,"<"&DATE($H$4,4,1)) | E15: =C15-D15 | F15: =SUMIFS(Kosten!$G$6:$G$2000,Kosten!$A$6:$A$2000,">="&DATE($H$4,1,1),Kosten!$A$6:$A$2000,"<"&DATE($H$4,4,1)) | G15: =E15-F15 | H15: =SUMIFS(Facturen!$O$6:$O$2000,Facturen!$Q$6:$Q$2000,">="&DATE($H$4,1,1),Facturen!$Q$6:$Q$2000,"<"&DATE($H$4,4,1))-SUMIFS(Facturen!$I$6:$I$2000,Facturen!$A$6:$A$2000,">="&DATE($H$4,1,1),Facturen!$A$6:$A$2000,"<"&DATE($H$4,4,1))-SUMIFS(Kosten!$I$6:$I$2000,Kosten!$A$6:$A$2000,">="&DATE($H$4,1,1),Kosten!$A$6:$A$2000,"<"&DATE($H$4,4,1))
B16: Q2 | C16: =SUMIFS(Facturen!$M$6:$M$2000,Facturen!$Q$6:$Q$2000,">="&DATE($H$4,4,1),Facturen!$Q$6:$Q$2000,"<"&DATE($H$4,7,1)) | D16: =SUMIFS(Facturen!$G$6:$G$2000,Facturen!$A$6:$A$2000,">="&DATE($H$4,4,1),Facturen!$A$6:$A$2000,"<"&DATE($H$4,7,1)) | E16: =C16-D16 | F16: =SUMIFS(Kosten!$G$6:$G$2000,Kosten!$A$6:$A$2000,">="&DATE($H$4,4,1),Kosten!$A$6:$A$2000,"<"&DATE($H$4,7,1)) | G16: =E16-F16 | H16: =SUMIFS(Facturen!$O$6:$O$2000,Facturen!$Q$6:$Q$2000,">="&DATE($H$4,4,1),Facturen!$Q$6:$Q$2000,"<"&DATE($H$4,7,1))-SUMIFS(Facturen!$I$6:$I$2000,Facturen!$A$6:$A$2000,">="&DATE($H$4,4,1),Facturen!$A$6:$A$2000,"<"&DATE($H$4,7,1))-SUMIFS(Kosten!$I$6:$I$2000,Kosten!$A$6:$A$2000,">="&DATE($H$4,4,1),Kosten!$A$6:$A$2000,"<"&DATE($H$4,7,1))
B17: Q3 | C17: =SUMIFS(Facturen!$M$6:$M$2000,Facturen!$Q$6:$Q$2000,">="&DATE($H$4,7,1),Facturen!$Q$6:$Q$2000,"<"&DATE($H$4,10,1)) | D17: =SUMIFS(Facturen!$G$6:$G$2000,Facturen!$A$6:$A$2000,">="&DATE($H$4,7,1),Facturen!$A$6:$A$2000,"<"&DATE($H$4,10,1)) | E17: =C17-D17 | F17: =SUMIFS(Kosten!$G$6:$G$2000,Kosten!$A$6:$A$2000,">="&DATE($H$4,7,1),Kosten!$A$6:$A$2000,"<"&DATE($H$4,10,1)) | G17: =E17-F17 | H17: =SUMIFS(Facturen!$O$6:$O$2000,Facturen!$Q$6:$Q$2000,">="&DATE($H$4,7,1),Facturen!$Q$6:$Q$2000,"<"&DATE($H$4,10,1))-SUMIFS(Facturen!$I$6:$I$2000,Facturen!$A$6:$A$2000,">="&DATE($H$4,7,1),Facturen!$A$6:$A$2000,"<"&DATE($H$4,10,1))-SUMIFS(Kosten!$I$6:$I$2000,Kosten!$A$6:$A$2000,">="&DATE($H$4,7,1),Kosten!$A$6:$A$2000,"<"&DATE($H$4,10,1))
B18: Q4 | C18: =SUMIFS(Facturen!$M$6:$M$2000,Facturen!$Q$6:$Q$2000,">="&DATE($H$4,10,1),Facturen!$Q$6:$Q$2000,"<"&DATE($H$4,13,1)) | D18: =SUMIFS(Facturen!$G$6:$G$2000,Facturen!$A$6:$A$2000,">="&DATE($H$4,10,1),Facturen!$A$6:$A$2000,"<"&DATE($H$4,13,1)) | E18: =C18-D18 | F18: =SUMIFS(Kosten!$G$6:$G$2000,Kosten!$A$6:$A$2000,">="&DATE($H$4,10,1),Kosten!$A$6:$A$2000,"<"&DATE($H$4,13,1)) | G18: =E18-F18 | H18: =SUMIFS(Facturen!$O$6:$O$2000,Facturen!$Q$6:$Q$2000,">="&DATE($H$4,10,1),Facturen!$Q$6:$Q$2000,"<"&DATE($H$4,13,1))-SUMIFS(Facturen!$I$6:$I$2000,Facturen!$A$6:$A$2000,">="&DATE($H$4,10,1),Facturen!$A$6:$A$2000,"<"&DATE($H$4,13,1))-SUMIFS(Kosten!$I$6:$I$2000,Kosten!$A$6:$A$2000,">="&DATE($H$4,10,1),Kosten!$A$6:$A$2000,"<"&DATE($H$4,13,1))
B19: Totaal | C19: =SUM(C15:C18) | D19: =SUM(D15:D18) | E19: =SUM(E15:E18) | F19: =SUM(F15:F18) | G19: =SUM(G15:G18) | H19: =SUM(H15:H18)
B22: Wat staat er nog open?
B23: incl btw, alle jaren
B24: Klanten moeten ons nog betalen | G24: =COUNTIF(Facturen!$T$6:$T$2000,"Wacht op klant")&IF(COUNTIF(Facturen!$T$6:$T$2000,"Wacht op klant")=1," factuur"," facturen") | H24: =SUMIFS(Facturen!$P$6:$P$2000,Facturen!$T$6:$T$2000,"Wacht op klant")
B25: Wij moeten freelancers nog betalen | G25: =COUNTIF(Facturen!$T$6:$T$2000,"Nog betalen")&IF(COUNTIF(Facturen!$T$6:$T$2000,"Nog betalen")=1," factuur"," facturen") | H25: =SUMIFS(Facturen!$J$6:$J$2000,Facturen!$T$6:$T$2000,"Nog betalen")
B26: Wij moeten kosten nog betalen | G26: =COUNTIF(Kosten!$L$6:$L$2000,"Nog betalen")&IF(COUNTIF(Kosten!$L$6:$L$2000,"Nog betalen")=1," factuur"," facturen") | H26: =SUMIFS(Kosten!$J$6:$J$2000,Kosten!$L$6:$L$2000,"Nog betalen")
B27: Freelancerfacturen nog niet doorgefactureerd | G27: =COUNTIF(Facturen!$T$6:$T$2000,"Nog factureren")&IF(COUNTIF(Facturen!$T$6:$T$2000,"Nog factureren")=1," factuur"," facturen") | H27: =SUMIFS(Facturen!$J$6:$J$2000,Facturen!$T$6:$T$2000,"Nog factureren")
B30: Zo werkt het
B31: 1. Factuur van een freelancer binnen? → tabblad Facturen, nieuwe regel: datum, naam, klant, factuurnr en bedrag ex btw.
B32: 2. Onze factuur aan de klant gemaakt? → zelfde regel: Q4S factuurnr, bedrag ex btw en de datum verstuurd.
B33: Eén Q4S-factuur voor meerdere freelancerfacturen? Zet hetzelfde Q4S-nummer op elke regel en het bedrag alleen op de eerste.
B34: 3. Betaald of geld binnen? → vul 'Betaald op' / 'Klant betaald op' in. De Status springt vanzelf naar Afgerond.
B35: 4. Eigen kosten (huur, software, tankpas …) → tabblad Kosten, kies een Soort.
B36: Grijze vakjes rekenen zelf — niet overschrijven. Omzet telt op 'Verstuurd op', inkoop en kosten op de factuurdatum.

Sheet Facturen
C1: Facturen
C2: Eén regel per factuur van een freelancer. Vul de witte vakjes in; de grijze rekenen zelf.
A4: WIE & WAT | F4: INKOOP · factuur van de freelancer | L4: VERKOOP · onze factuur aan de klant | S4: RESULTAAT
A5: Ontvangen op | B5: Kwartaal | C5: Freelancer | D5: Klant / project | E5: Weken / opmerking | F5: Factuurnr | G5: Inkoop ex btw | H5: Btw % | I5: Btw inkoop | J5: Inkoop incl btw | K5: Betaald op | L5: Q4S factuurnr | M5: Verkoop ex btw | N5: Btw % klant | O5: Btw verkoop | P5: Verkoop incl btw | Q5: Verstuurd op | R5: Klant betaald op | S5: Marge ex btw | T5: Status
B6: =IF(A6="","",YEAR(A6)&" Q"&ROUNDUP(MONTH(A6)/3,0)) | I6: =IF(G6="","",ROUND(G6*H6,2)) | J6: =IF(G6="","",G6+N(I6)) | O6: =IF(M6="","",ROUND(M6*N6,2)) | P6: =IF(M6="","",M6+N(O6)) | S6: =IF(L6="","",IF(COUNTIF(L$6:L6,L6)>1,"",SUMIF(L$6:L$2000,L6,M$6:M$2000)-SUMIF(L$6:L$2000,L6,G$6:G$2000))) | T6: =IF(AND(C6="",G6=""),"",IF(L6="","Nog factureren",IF(AND(G6<>"",OR(K6="",K6>TODAY())),"Nog betalen",IF(OR(R6="",R6>TODAY()),"Wacht op klant","Afgerond"))))
B7: =IF(A7="","",YEAR(A7)&" Q"&ROUNDUP(MONTH(A7)/3,0)) | I7: =IF(G7="","",ROUND(G7*H7,2)) | J7: =IF(G7="","",G7+N(I7)) | O7: =IF(M7="","",ROUND(M7*N7,2)) | P7: =IF(M7="","",M7+N(O7)) | S7: =IF(L7="","",IF(COUNTIF(L$6:L7,L7)>1,"",SUMIF(L$6:L$2000,L7,M$6:M$2000)-SUMIF(L$6:L$2000,L7,G$6:G$2000))) | T7: =IF(AND(C7="",G7=""),"",IF(L7="","Nog factureren",IF(AND(G7<>"",OR(K7="",K7>TODAY())),"Nog betalen",IF(OR(R7="",R7>TODAY()),"Wacht op klant","Afgerond"))))
B8: =IF(A8="","",YEAR(A8)&" Q"&ROUNDUP(MONTH(A8)/3,0)) | I8: =IF(G8="","",ROUND(G8*H8,2)) | J8: =IF(G8="","",G8+N(I8)) | O8: =IF(M8="","",ROUND(M8*N8,2)) | P8: =IF(M8="","",M8+N(O8)) | S8: =IF(L8="","",IF(COUNTIF(L$6:L8,L8)>1,"",SUMIF(L$6:L$2000,L8,M$6:M$2000)-SUMIF(L$6:L$2000,L8,G$6:G$2000))) | T8: =IF(AND(C8="",G8=""),"",IF(L8="","Nog factureren",IF(AND(G8<>"",OR(K8="",K8>TODAY())),"Nog betalen",IF(OR(R8="",R8>TODAY()),"Wacht op klant","Afgerond"))))
B9: =IF(A9="","",YEAR(A9)&" Q"&ROUNDUP(MONTH(A9)/3,0)) | I9: =IF(G9="","",ROUND(G9*H9,2)) | J9: =IF(G9="","",G9+N(I9)) | O9: =IF(M9="","",ROUND(M9*N9,2)) | P9: =IF(M9="","",M9+N(O9)) | S9: =IF(L9="","",IF(COUNTIF(L$6:L9,L9)>1,"",SUMIF(L$6:L$2000,L9,M$6:M$2000)-SUMIF(L$6:L$2000,L9,G$6:G$2000))) | T9: =IF(AND(C9="",G9=""),"",IF(L9="","Nog factureren",IF(AND(G9<>"",OR(K9="",K9>TODAY())),"Nog betalen",IF(OR(R9="",R9>TODAY()),"Wacht op klant","Afgerond"))))
B10: =IF(A10="","",YEAR(A10)&" Q"&ROUNDUP(MONTH(A10)/3,0)) | I10: =IF(G10="","",ROUND(G10*H10,2)) | J10: =IF(G10="","",G10+N(I10)) | O10: =IF(M10="","",ROUND(M10*N10,2)) | P10: =IF(M10="","",M10+N(O10)) | S10: =IF(L10="","",IF(COUNTIF(L$6:L10,L10)>1,"",SUMIF(L$6:L$2000,L10,M$6:M$2000)-SUMIF(L$6:L$2000,L10,G$6:G$2000))) | T10: =IF(AND(C10="",G10=""),"",IF(L10="","Nog factureren",IF(AND(G10<>"",OR(K10="",K10>TODAY())),"Nog betalen",IF(OR(R10="",R10>TODAY()),"Wacht op klant","Afgerond"))))
B11: =IF(A11="","",YEAR(A11)&" Q"&ROUNDUP(MONTH(A11)/3,0)) | I11: =IF(G11="","",ROUND(G11*H11,2)) | J11: =IF(G11="","",G11+N(I11)) | O11: =IF(M11="","",ROUND(M11*N11,2)) | P11: =IF(M11="","",M11+N(O11)) | S11: =IF(L11="","",IF(COUNTIF(L$6:L11,L11)>1,"",SUMIF(L$6:L$2000,L11,M$6:M$2000)-SUMIF(L$6:L$2000,L11,G$6:G$2000))) | T11: =IF(AND(C11="",G11=""),"",IF(L11="","Nog factureren",IF(AND(G11<>"",OR(K11="",K11>TODAY())),"Nog betalen",IF(OR(R11="",R11>TODAY()),"Wacht op klant","Afgerond"))))
B12: =IF(A12="","",YEAR(A12)&" Q"&ROUNDUP(MONTH(A12)/3,0)) | I12: =IF(G12="","",ROUND(G12*H12,2)) | J12: =IF(G12="","",G12+N(I12)) | O12: =IF(M12="","",ROUND(M12*N12,2)) | P12: =IF(M12="","",M12+N(O12)) | S12: =IF(L12="","",IF(COUNTIF(L$6:L12,L12)>1,"",SUMIF(L$6:L$2000,L12,M$6:M$2000)-SUMIF(L$6:L$2000,L12,G$6:G$2000))) | T12: =IF(AND(C12="",G12=""),"",IF(L12="","Nog factureren",IF(AND(G12<>"",OR(K12="",K12>TODAY())),"Nog betalen",IF(OR(R12="",R12>TODAY()),"Wacht op klant","Afgerond"))))
B13: =IF(A13="","",YEAR(A13)&" Q"&ROUNDUP(MONTH(A13)/3,0)) | I13: =IF(G13="","",ROUND(G13*H13,2)) | J13: =IF(G13="","",G13+N(I13)) | O13: =IF(M13="","",ROUND(M13*N13,2)) | P13: =IF(M13="","",M13+N(O13)) | S13: =IF(L13="","",IF(COUNTIF(L$6:L13,L13)>1,"",SUMIF(L$6:L$2000,L13,M$6:M$2000)-SUMIF(L$6:L$2000,L13,G$6:G$2000))) | T13: =IF(AND(C13="",G13=""),"",IF(L13="","Nog factureren",IF(AND(G13<>"",OR(K13="",K13>TODAY())),"Nog betalen",IF(OR(R13="",R13>TODAY()),"Wacht op klant","Afgerond"))))
B14: =IF(A14="","",YEAR(A14)&" Q"&ROUNDUP(MONTH(A14)/3,0)) | I14: =IF(G14="","",ROUND(G14*H14,2)) | J14: =IF(G14="","",G14+N(I14)) | O14: =IF(M14="","",ROUND(M14*N14,2)) | P14: =IF(M14="","",M14+N(O14)) | S14: =IF(L14="","",IF(COUNTIF(L$6:L14,L14)>1,"",SUMIF(L$6:L$2000,L14,M$6:M$2000)-SUMIF(L$6:L$2000,L14,G$6:G$2000))) | T14: =IF(AND(C14="",G14=""),"",IF(L14="","Nog factureren",IF(AND(G14<>"",OR(K14="",K14>TODAY())),"Nog betalen",IF(OR(R14="",R14>TODAY()),"Wacht op klant","Afgerond"))))
B15: =IF(A15="","",YEAR(A15)&" Q"&ROUNDUP(MONTH(A15)/3,0)) | I15: =IF(G15="","",ROUND(G15*H15,2)) | J15: =IF(G15="","",G15+N(I15)) | O15: =IF(M15="","",ROUND(M15*N15,2)) | P15: =IF(M15="","",M15+N(O15)) | S15: =IF(L15="","",IF(COUNTIF(L$6:L15,L15)>1,"",SUMIF(L$6:L$2000,L15,M$6:M$2000)-SUMIF(L$6:L$2000,L15,G$6:G$2000))) | T15: =IF(AND(C15="",G15=""),"",IF(L15="","Nog factureren",IF(AND(G15<>"",OR(K15="",K15>TODAY())),"Nog betalen",IF(OR(R15="",R15>TODAY()),"Wacht op klant","Afgerond"))))
B16: =IF(A16="","",YEAR(A16)&" Q"&ROUNDUP(MONTH(A16)/3,0)) | I16: =IF(G16="","",ROUND(G16*H16,2)) | J16: =IF(G16="","",G16+N(I16)) | O16: =IF(M16="","",ROUND(M16*N16,2)) | P16: =IF(M16="","",M16+N(O16)) | S16: =IF(L16="","",IF(COUNTIF(L$6:L16,L16)>1,"",SUMIF(L$6:L$2000,L16,M$6:M$2000)-SUMIF(L$6:L$2000,L16,G$6:G$2000))) | T16: =IF(AND(C16="",G16=""),"",IF(L16="","Nog factureren",IF(AND(G16<>"",OR(K16="",K16>TODAY())),"Nog betalen",IF(OR(R16="",R16>TODAY()),"Wacht op klant","Afgerond"))))
B17: =IF(A17="","",YEAR(A17)&" Q"&ROUNDUP(MONTH(A17)/3,0)) | I17: =IF(G17="","",ROUND(G17*H17,2)) | J17: =IF(G17="","",G17+N(I17)) | O17: =IF(M17="","",ROUND(M17*N17,2)) | P17: =IF(M17="","",M17+N(O17)) | S17: =IF(L17="","",IF(COUNTIF(L$6:L17,L17)>1,"",SUMIF(L$6:L$2000,L17,M$6:M$2000)-SUMIF(L$6:L$2000,L17,G$6:G$2000))) | T17: =IF(AND(C17="",G17=""),"",IF(L17="","Nog factureren",IF(AND(G17<>"",OR(K17="",K17>TODAY())),"Nog betalen",IF(OR(R17="",R17>TODAY()),"Wacht op klant","Afgerond"))))
... B1505: =IF(A1505="","",YEAR(A1505)&" Q"&ROUNDUP(MONTH(A1505)/3,0)) | I1505: =IF(G1505="","",ROUND(G1505*H1505,2)) | J1505: =IF(G1505="","",G1505+N(I1505)) | O1505: =IF(M1505="","",ROUND(M1505*N1505,2)) | P1505: =IF(M1505="","",M1505+N(O1505)) | S1505: =IF(L1505="","",IF(COUNTIF(L$6:L1505,L1505)>1,"",SUMIF(L$6:L$2000,L1505,M$6:M$2000)-SUMIF(L$6:L$2000,L1505,G$6:G$2000))) | T1505: =IF(AND(C1505="",G1505=""),"",IF(L1505="","Nog factureren",IF(AND(G1505<>"",OR(K1505="",K1505>TODAY())),"Nog betalen",IF(OR(R1505="",R1505>TODAY()),"Wacht op klant","Afgerond"))))

Sheet Kosten
C1: Kosten
C2: Alle eigen kosten van Q4S: huur, software, auto, verzekeringen … Kies bij Soort een categorie.
A4: KOSTEN · wat Q4S zelf betaalt
A5: Datum | B5: Kwartaal | C5: Leverancier | D5: Omschrijving | E5: Soort | F5: Factuurnr | G5: Bedrag ex btw | H5: Btw % | I5: Btw € | J5: Totaal incl btw | K5: Betaald op | L5: Status
B6: =IF(A6="","",YEAR(A6)&" Q"&ROUNDUP(MONTH(A6)/3,0)) | I6: =IF(G6="","",ROUND(G6*H6,2)) | J6: =IF(G6="","",G6+N(I6)) | L6: =IF(G6="","",IF(OR(K6="",K6>TODAY()),"Nog betalen","Betaald"))
B7: =IF(A7="","",YEAR(A7)&" Q"&ROUNDUP(MONTH(A7)/3,0)) | I7: =IF(G7="","",ROUND(G7*H7,2)) | J7: =IF(G7="","",G7+N(I7)) | L7: =IF(G7="","",IF(OR(K7="",K7>TODAY()),"Nog betalen","Betaald"))
B8: =IF(A8="","",YEAR(A8)&" Q"&ROUNDUP(MONTH(A8)/3,0)) | I8: =IF(G8="","",ROUND(G8*H8,2)) | J8: =IF(G8="","",G8+N(I8)) | L8: =IF(G8="","",IF(OR(K8="",K8>TODAY()),"Nog betalen","Betaald"))
B9: =IF(A9="","",YEAR(A9)&" Q"&ROUNDUP(MONTH(A9)/3,0)) | I9: =IF(G9="","",ROUND(G9*H9,2)) | J9: =IF(G9="","",G9+N(I9)) | L9: =IF(G9="","",IF(OR(K9="",K9>TODAY()),"Nog betalen","Betaald"))
B10: =IF(A10="","",YEAR(A10)&" Q"&ROUNDUP(MONTH(A10)/3,0)) | I10: =IF(G10="","",ROUND(G10*H10,2)) | J10: =IF(G10="","",G10+N(I10)) | L10: =IF(G10="","",IF(OR(K10="",K10>TODAY()),"Nog betalen","Betaald"))
B11: =IF(A11="","",YEAR(A11)&" Q"&ROUNDUP(MONTH(A11)/3,0)) | I11: =IF(G11="","",ROUND(G11*H11,2)) | J11: =IF(G11="","",G11+N(I11)) | L11: =IF(G11="","",IF(OR(K11="",K11>TODAY()),"Nog betalen","Betaald"))
B12: =IF(A12="","",YEAR(A12)&" Q"&ROUNDUP(MONTH(A12)/3,0)) | I12: =IF(G12="","",ROUND(G12*H12,2)) | J12: =IF(G12="","",G12+N(I12)) | L12: =IF(G12="","",IF(OR(K12="",K12>TODAY()),"Nog betalen","Betaald"))
B13: =IF(A13="","",YEAR(A13)&" Q"&ROUNDUP(MONTH(A13)/3,0)) | I13: =IF(G13="","",ROUND(G13*H13,2)) | J13: =IF(G13="","",G13+N(I13)) | L13: =IF(G13="","",IF(OR(K13="",K13>TODAY()),"Nog betalen","Betaald"))
B14: =IF(A14="","",YEAR(A14)&" Q"&ROUNDUP(MONTH(A14)/3,0)) | I14: =IF(G14="","",ROUND(G14*H14,2)) | J14: =IF(G14="","",G14+N(I14)) | L14: =IF(G14="","",IF(OR(K14="",K14>TODAY()),"Nog betalen","Betaald"))
B15: =IF(A15="","",YEAR(A15)&" Q"&ROUNDUP(MONTH(A15)/3,0)) | I15: =IF(G15="","",ROUND(G15*H15,2)) | J15: =IF(G15="","",G15+N(I15)) | L15: =IF(G15="","",IF(OR(K15="",K15>TODAY()),"Nog betalen","Betaald"))
B16: =IF(A16="","",YEAR(A16)&" Q"&ROUNDUP(MONTH(A16)/3,0)) | I16: =IF(G16="","",ROUND(G16*H16,2)) | J16: =IF(G16="","",G16+N(I16)) | L16: =IF(G16="","",IF(OR(K16="",K16>TODAY()),"Nog betalen","Betaald"))
B17: =IF(A17="","",YEAR(A17)&" Q"&ROUNDUP(MONTH(A17)/3,0)) | I17: =IF(G17="","",ROUND(G17*H17,2)) | J17: =IF(G17="","",G17+N(I17)) | L17: =IF(G17="","",IF(OR(K17="",K17>TODAY()),"Nog betalen","Betaald"))
... B805: =IF(A805="","",YEAR(A805)&" Q"&ROUNDUP(MONTH(A805)/3,0)) | I805: =IF(G805="","",ROUND(G805*H805,2)) | J805: =IF(G805="","",G805+N(I805)) | L805: =IF(G805="","",IF(OR(K805="",K805>TODAY()),"Nog betalen","Betaald"))

Sheet Lijsten
A1: Soorten kosten
A2: Huur & kantoor
A3: Software & abonnementen
A4: Auto & reizen
A5: Verzekeringen
A6: Marketing & werving
A7: Advies, boekhouder & juridisch
A8: Bank & rente
A9: Opleiding & certificering
A10: Belastingen
A11: Personeel
A12: Declaraties
A13: Overig
